{"results": [{"round": 1, "tally": {"Alexa Aviles": 4796.0, "Yu Lin": 3111.0, "Rodrigo G. Camarena": 1395.0, "Jacqui Painter": 1189.0, "Cesar Zuniga": 1083.0, "Victor Swinton": 489.0, "Write-ins": 33.0, "Inactive Ballots": 0.0}, "tallyResults": [{"eliminated": "Write-ins"}]}, {"round": 2, "tally": {"Alexa Aviles": 4798.0, "Yu Lin": 3117.0, "Rodrigo G. Camarena": 1398.0, "Jacqui Painter": 1190.0, "Cesar Zuniga": 1085.0, "Victor Swinton": 489.0, "Inactive Ballots": 19.0}, "tallyResults": [{"eliminated": "Victor Swinton"}]}, {"round": 3, "tally": {"Alexa Aviles": 4859.0, "Yu Lin": 3174.0, "Rodrigo G. Camarena": 1421.0, "Jacqui Painter": 1281.0, "Cesar Zuniga": 1151.0, "Inactive Ballots": 210.0}, "tallyResults": [{"eliminated": "Cesar Zuniga"}]}, {"round": 4, "tally": {"Alexa Aviles": 5195.0, "Yu Lin": 3288.0, "Rodrigo G. Camarena": 1616.0, "Jacqui Painter": 1460.0, "Inactive Ballots": 537.0}, "tallyResults": [{"eliminated": "Rodrigo G. Camarena"}, {"eliminated": "Jacqui Painter"}]}, {"round": 5, "tally": {"Alexa Aviles": 6843.0, "Yu Lin": 3680.0, "Inactive Ballots": 1573.0}, "tallyResults": [{"elected": "Alexa Aviles"}]}], "config": {"contest": "New York City DEM Council Member 38th Council District", "date": "2021-06-22", "jurisdiction": "New York City", "threshold": 5261.5}}