{"results": [{"round": 1, "tally": {"Rita C. Joseph": 5114.0, "Josue Pierre": 4124.0, "Kenya Handy-Hilliard": 3885.0, "Edwin K. Raymond": 1650.0, "Cecilia Cortez": 1509.0, "Blake Morris": 1024.0, "Maxi Eugene": 1015.0, "Harriet L. Hines": 633.0, "John Williams": 613.0, "Vivia M. Morgan": 372.0, "Victor Jordan": 307.0, "Write-ins": 49.0, "Inactive Ballots": 0.0}, "tallyResults": [{"eliminated": "Write-ins"}]}, {"round": 2, "tally": {"Rita C. Joseph": 5115.0, "Josue Pierre": 4127.0, "Kenya Handy-Hilliard": 3890.0, "Edwin K. Raymond": 1653.0, "Cecilia Cortez": 1511.0, "Blake Morris": 1026.0, "Maxi Eugene": 1015.0, "Harriet L. Hines": 634.0, "John Williams": 613.0, "Vivia M. Morgan": 372.0, "Victor Jordan": 308.0, "Inactive Ballots": 31.0}, "tallyResults": [{"eliminated": "Victor Jordan"}]}, {"round": 3, "tally": {"Rita C. Joseph": 5181.0, "Josue Pierre": 4150.0, "Kenya Handy-Hilliard": 3903.0, "Edwin K. Raymond": 1678.0, "Cecilia Cortez": 1530.0, "Blake Morris": 1051.0, "Maxi Eugene": 1026.0, "Harriet L. Hines": 652.0, "John Williams": 627.0, "Vivia M. Morgan": 387.0, "Inactive Ballots": 110.0}, "tallyResults": [{"eliminated": "Vivia M. Morgan"}]}, {"round": 4, "tally": {"Rita C. Joseph": 5220.0, "Josue Pierre": 4176.0, "Kenya Handy-Hilliard": 3943.0, "Edwin K. Raymond": 1702.0, "Cecilia Cortez": 1593.0, "Blake Morris": 1066.0, "Maxi Eugene": 1041.0, "Harriet L. Hines": 687.0, "John Williams": 655.0, "Inactive Ballots": 212.0}, "tallyResults": [{"eliminated": "John Williams"}]}, {"round": 5, "tally": {"Rita C. Joseph": 5270.0, "Josue Pierre": 4232.0, "Kenya Handy-Hilliard": 4005.0, "Edwin K. Raymond": 1758.0, "Cecilia Cortez": 1650.0, "Blake Morris": 1128.0, "Maxi Eugene": 1081.0, "Harriet L. Hines": 722.0, "Inactive Ballots": 449.0}, "tallyResults": [{"eliminated": "Harriet L. Hines"}]}, {"round": 6, "tally": {"Rita C. Joseph": 5429.0, "Josue Pierre": 4292.0, "Kenya Handy-Hilliard": 4067.0, "Edwin K. Raymond": 1840.0, "Cecilia Cortez": 1733.0, "Blake Morris": 1187.0, "Maxi Eugene": 1124.0, "Inactive Ballots": 623.0}, "tallyResults": [{"eliminated": "Maxi Eugene"}]}, {"round": 7, "tally": {"Rita C. Joseph": 5575.0, "Josue Pierre": 4475.0, "Kenya Handy-Hilliard": 4151.0, "Edwin K. Raymond": 1913.0, "Cecilia Cortez": 1814.0, "Blake Morris": 1254.0, "Inactive Ballots": 1113.0}, "tallyResults": [{"eliminated": "Blake Morris"}]}, {"round": 8, "tally": {"Rita C. Joseph": 5796.0, "Josue Pierre": 4673.0, "Kenya Handy-Hilliard": 4290.0, "Edwin K. Raymond": 2026.0, "Cecilia Cortez": 2029.0, "Inactive Ballots": 1481.0}, "tallyResults": [{"eliminated": "Edwin K. Raymond"}, {"eliminated": "Cecilia Cortez"}]}, {"round": 9, "tally": {"Rita C. Joseph": 6822.0, "Josue Pierre": 5371.0, "Kenya Handy-Hilliard": 5000.0, "Inactive Ballots": 3102.0}, "tallyResults": [{"eliminated": "Kenya Handy-Hilliard"}]}, {"round": 10, "tally": {"Rita C. Joseph": 9072.0, "Josue Pierre": 6228.0, "Inactive Ballots": 4995.0}, "tallyResults": [{"elected": "Rita C. Joseph"}]}], "config": {"contest": "New York City DEM Council Member 40th Council District", "date": "2021-06-22", "jurisdiction": "New York City", "threshold": 7650.0}}