{"results": [{"round": 1, "tally": {"Steven Saperstein": 3028.0, "Mariya Markh": 2575.0, "Amber L. Adler": 1582.0, "Binyomin Zev Bendet": 1484.0, "Heshy Tischler": 461.0, "Write-ins": 67.0, "Inactive Ballots": 0.0}, "tallyResults": [{"eliminated": "Write-ins", "transfers": {"Steven Saperstein": 8.0, "Mariya Markh": 10.0, "Amber L. Adler": 7.0, "Binyomin Zev Bendet": 2.0, "Heshy Tischler": 2.0, "Inactive Ballots": 38.0}}]}, {"round": 2, "tally": {"Steven Saperstein": 3036.0, "Mariya Markh": 2585.0, "Amber L. Adler": 1589.0, "Binyomin Zev Bendet": 1486.0, "Heshy Tischler": 463.0, "Inactive Ballots": 38.0}, "tallyResults": [{"eliminated": "Heshy Tischler", "transfers": {"Steven Saperstein": 117.0, "Mariya Markh": 56.0, "Amber L. Adler": 50.0, "Binyomin Zev Bendet": 102.0, "Inactive Ballots": 138.0}}]}, {"round": 3, "tally": {"Steven Saperstein": 3153.0, "Mariya Markh": 2641.0, "Amber L. Adler": 1639.0, "Binyomin Zev Bendet": 1588.0, "Inactive Ballots": 176.0}, "tallyResults": [{"eliminated": "Binyomin Zev Bendet", "transfers": {"Steven Saperstein": 629.0, "Mariya Markh": 219.0, "Amber L. Adler": 359.0, "Inactive Ballots": 381.0}}]}, {"round": 4, "tally": {"Steven Saperstein": 3782.0, "Mariya Markh": 2860.0, "Amber L. Adler": 1998.0, "Inactive Ballots": 557.0}, "tallyResults": [{"eliminated": "Amber L. Adler", "transfers": {"Steven Saperstein": 752.0, "Mariya Markh": 554.0, "Inactive Ballots": 692.0}}]}, {"round": 5, "tally": {"Steven Saperstein": 4534.0, "Mariya Markh": 3414.0, "Inactive Ballots": 1249.0}, "tallyResults": [{"elected": "Steven Saperstein"}]}], "config": {"contest": "New York City DEM Council Member 48th Council District", "date": "2021-06-22", "jurisdiction": "New York City", "threshold": 3974.0}}